python3_utils/__init__.py
python3_utils/decorators.py
python3_utils/version.py
python3_utils/tests/__init__.py
python3_utils/tests/decorator_py2_tests.py
python3_utils/tests/decorator_tests.py
python3_utils-0.4.0.dist-info/DESCRIPTION.rst
python3_utils-0.4.0.dist-info/METADATA
python3_utils-0.4.0.dist-info/metadata.json
python3_utils-0.4.0.dist-info/RECORD
python3_utils-0.4.0.dist-info/top_level.txt
python3_utils-0.4.0.dist-info/WHEEL
