Metadata-Version: 1.1
Name: python3-utils
Version: 0.4.0
Summary: Useful collection of python3 utilities
Home-page: https://github.com/micahhausler/python3-utils
Author: Micah Hausler
Author-email: hausler.m@gmail.com
License: MIT
Platform: UNKNOWN
Classifier: Programming Language :: Python :: 2.7
Classifier: Programming Language :: Python :: 3.3
Classifier: Programming Language :: Python :: 3.4
Classifier: Intended Audience :: Developers
Classifier: License :: OSI Approved :: MIT License
Classifier: Operating System :: OS Independent
